ron_swanson/__init__.py
ron_swanson/api.py
ron_swanson_client-0.1.dist-info/LICENSE
ron_swanson_client-0.1.dist-info/WHEEL
ron_swanson_client-0.1.dist-info/METADATA
ron_swanson_client-0.1.dist-info/RECORD
