Metadata-Version: 2.1
Name: ron-swanson-client
Version: 0.1
Summary: Ron Swanson quotes API client
Author-email: Mikhail Kravets <michkravets@gmail.com>
Requires-Python: >=3.7
Classifier: License :: OSI Approved :: MIT License
Requires-Dist: requests >= 2.27, < 3.0
Project-URL: Home, https://github.com/MikhailKravets/ron-swanson-client
